pygal_maps_ua/UKR-ADM1_simplified.Svg
pygal_maps_ua/UKR-ADM1_simplified_ordlo.Svg
pygal_maps_ua/__init__.py
pygal_maps_ua/maps.py
pygal_maps_ua/test/__init__.py
pygal_maps_ua/test/test_maps.py
pygal_maps_ua-1.0.2.dist-info/LICENSE
pygal_maps_ua-1.0.2.dist-info/METADATA
pygal_maps_ua-1.0.2.dist-info/WHEEL
pygal_maps_ua-1.0.2.dist-info/entry_points.txt
pygal_maps_ua-1.0.2.dist-info/top_level.txt
pygal_maps_ua-1.0.2.dist-info/RECORD
