Metadata-Version: 2.1
Name: pygal-maps-ua
Version: 1.0.2
Summary: Ukraine maps for pygal
Home-page: http://github.com/Golova1111/pygal_maps_ua
Author: Vadym Holovashchenko
Author-email: vadym.holovashchenko@gmail.com
License: GNU LGPL v3+
Keywords: svg,chart,graph,maps,ukraine,pygal
Platform: Any
Classifier: Development Status :: 4 - Beta
Classifier: Environment :: Console
Classifier: Intended Audience :: End Users/Desktop
Classifier: License :: OSI Approved :: GNU Lesser General Public License v3 or later (LGPLv3+)
Classifier: Operating System :: OS Independent
Classifier: Programming Language :: Python :: 2
Classifier: Programming Language :: Python :: 3
Classifier: Topic :: Multimedia :: Graphics :: Presentation
Provides: pygal_maps_ua
License-File: LICENSE
Requires-Dist: pygal (>=1.9.9)
